ocr_map/__init__.py
ocr_map/__init__.pyi
ocr_map/cli.py
ocr_map/known.py
ocr_map/model.py
ocr_map/parse.py
ocr_map/types.py
ocr_map/unknown.py
ocr_map-0.1.7.dist-info/METADATA
ocr_map-0.1.7.dist-info/WHEEL
ocr_map-0.1.7.dist-info/entry_points.txt
ocr_map-0.1.7.dist-info/top_level.txt
ocr_map-0.1.7.dist-info/RECORD
