Metadata-Version: 2.1
Name: ocr-map
Version: 0.1.7
Summary: Mapping OCR predictions to fixed-size vocabularies
Author-email: Marcel Claramunt <marcel@moveread.com>
Project-URL: repo, https://github.com/moveread/REPO.git
Requires-Python: >=3.10
Requires-Dist: editdistance
Provides-Extra: cli
Requires-Dist: typer ; extra == 'cli'
Requires-Dist: orjson ; extra == 'cli'
